{
    "APP001": {
        "领域": "感知觉统合",
        "子功能": "感觉刺激与调节模式",
        "应用名称": "奇妙的声音",
        "应用路径": "flash/XC001.exe",
        "图标路径": "icons/APP001.png"
    },
    "APP002": {
        "领域": "感知觉统合",
        "子功能": "感觉刺激与调节模式",
        "应用名称": "触感沙",
        "应用路径": "flash/XC002.exe",
        "图标路径": "icons/APP002.png"
    },
    "APP003": {
        "领域": "感知觉统合",
        "子功能": "感觉刺激与调节模式",
        "应用名称": "影子感知",
        "应用路径": "flash/XC003.exe",
        "图标路径": "icons/APP003.png"
    },
    "APP004": {
        "领域": "感知觉统合",
        "子功能": "感觉刺激与调节模式",
        "应用名称": "小小海绵",
        "应用路径": "flash/XC004.exe",
        "图标路径": "icons/APP004.png"
    },
    "APP005": {
        "领域": "感知觉统合",
        "子功能": "感觉刺激与调节模式",
        "应用名称": "下雨啦",
        "应用路径": "flash/XC005.exe",
        "图标路径": "icons/APP005.png"
    },
    "APP006": {
        "领域": "感知觉统合",
        "子功能": "感觉刺激与调节模式",
        "应用名称": "天气夏天",
        "应用路径": "flash/XC006.exe",
        "图标路径": "icons/APP006.png"
    },
    "APP007": {
        "领域": "感知觉统合",
        "子功能": "感觉刺激与调节模式",
        "应用名称": "感触风",
        "应用路径": "flash/XC007.exe",
        "图标路径": "icons/APP007.png"
    },
    "APP008": {
        "领域": "感知觉统合",
        "子功能": "感觉刺激与调节模式",
        "应用名称": "轮子圆圆的",
        "应用路径": "flash/XC008.exe",
        "图标路径": "icons/APP008.png"
    },
    "APP009": {
        "领域": "感知觉统合",
        "子功能": "感觉刺激与调节模式",
        "应用名称": "转动的乐趣",
        "应用路径": "flash/XC009.exe",
        "图标路径": "icons/APP009.png"
    },
    "APP010": {
        "领域": "感知觉统合",
        "子功能": "感觉刺激与调节模式",
        "应用名称": "冰冰凉凉",
        "应用路径": "flash/XC010.exe",
        "图标路径": "icons/APP010.png"
    },
    "APP011": {
        "领域": "感知觉统合",
        "子功能": "感觉刺激与调节模式",
        "应用名称": "火山喷发",
        "应用路径": "flash/XC011.exe",
        "图标路径": "icons/APP011.png"
    },
    "APP012": {
        "领域": "感知觉统合",
        "子功能": "感觉刺激与调节模式",
        "应用名称": "牛牛不一样",
        "应用路径": "flash/XC012.exe",
        "图标路径": "icons/APP012.png"
    },
    "APP013": {
        "领域": "感知觉统合",
        "子功能": "感觉刺激与调节模式",
        "应用名称": "柳树姑娘辫子长",
        "应用路径": "flash/XC013.exe",
        "图标路径": "icons/APP013.png"
    },
    "APP014": {
        "领域": "感知觉统合",
        "子功能": "感觉刺激与调节模式",
        "应用名称": "眼耳口鼻",
        "应用路径": "flash/XC014.exe",
        "图标路径": "icons/APP014.png"
    },
    "APP015": {
        "领域": "感知觉统合",
        "子功能": "感觉刺激与调节模式",
        "应用名称": "西瓜真甜",
        "应用路径": "flash/XC015.exe",
        "图标路径": "icons/APP015.png"
    },
    "APP016": {
        "领域": "感知觉统合",
        "子功能": "感觉刺激与调节模式",
        "应用名称": "春雨沙沙",
        "应用路径": "flash/XC016.exe",
        "图标路径": "icons/APP016.png"
    },
    "APP017": {
        "领域": "感知觉统合",
        "子功能": "感觉刺激与调节模式",
        "应用名称": "大小",
        "应用路径": "flash/XC017.exe",
        "图标路径": "icons/APP017.png"
    },
    "APP018": {
        "领域": "感知觉统合",
        "子功能": "感觉刺激与调节模式",
        "应用名称": "许多小鱼游来了",
        "应用路径": "flash/XC018.exe",
        "图标路径": "icons/APP018.png"
    },
    "APP019": {
        "领域": "感知觉统合",
        "子功能": "感觉刺激与调节模式",
        "应用名称": "青蛙合唱",
        "应用路径": "flash/XC019.exe",
        "图标路径": "icons/APP019.png"
    },
    "APP020": {
        "领域": "感知觉统合",
        "子功能": "感觉刺激与调节模式",
        "应用名称": "母鸭带小鸭",
        "应用路径": "flash/XC020.exe",
        "图标路径": "icons/APP020.png"
    },
    "APP021": {
        "领域": "感知觉统合",
        "子功能": "感觉刺激与调节模式",
        "应用名称": "蜜蜂做工",
        "应用路径": "flash/XC021.exe",
        "图标路径": "icons/APP021.png"
    },
    "APP022": {
        "领域": "感知觉统合",
        "子功能": "感觉刺激与调节模式",
        "应用名称": "开火车",
        "应用路径": "flash/XC022.exe",
        "图标路径": "icons/APP022.png"
    },
    "APP023": {
        "领域": "感知觉统合",
        "子功能": "感觉刺激与调节模式",
        "应用名称": "睡吧，小宝贝",
        "应用路径": "flash/XC023.exe",
        "图标路径": "icons/APP023.png"
    },
    "APP024": {
        "领域": "感知觉统合",
        "子功能": "感觉刺激与调节模式",
        "应用名称": "小小蛋儿把门开",
        "应用路径": "flash/XC024.exe",
        "图标路径": "icons/APP024.png"
    },
    "APP025": {
        "领域": "感知觉统合",
        "子功能": "感觉刺激与调节模式",
        "应用名称": "狗熊和蜜蜂",
        "应用路径": "flash/XC025.exe",
        "图标路径": "icons/APP025.png"
    },
    "APP026": {
        "领域": "感知觉统合",
        "子功能": "感觉刺激与调节模式",
        "应用名称": "洋娃娃跳舞",
        "应用路径": "flash/XC026.exe",
        "图标路径": "icons/APP026.png"
    },
    "APP027": {
        "领域": "感知觉统合",
        "子功能": "感觉刺激与调节模式",
        "应用名称": "打字机",
        "应用路径": "flash/XC027.exe",
        "图标路径": "icons/APP027.png"
    },
    "APP028": {
        "领域": "感知觉统合",
        "子功能": "感觉刺激与调节模式",
        "应用名称": "雷雨",
        "应用路径": "flash/XC028.exe",
        "图标路径": "icons/APP028.png"
    },
    "APP029": {
        "领域": "感知觉统合",
        "子功能": "感觉刺激与调节模式",
        "应用名称": "彝家娃娃真幸福",
        "应用路径": "flash/XC029.exe",
        "图标路径": "icons/APP029.png"
    },
    "APP030": {
        "领域": "感知觉统合",
        "子功能": "感觉刺激与调节模式",
        "应用名称": "有趣的洗衣机",
        "应用路径": "flash/XC030.exe",
        "图标路径": "icons/APP030.png"
    },
    "APP031": {
        "领域": "感知觉统合",
        "子功能": "感觉刺激与调节模式",
        "应用名称": "盆碗碟杯在唱歌",
        "应用路径": "flash/XC031.exe",
        "图标路径": "icons/APP031.png"
    },
    "APP032": {
        "领域": "感知觉统合",
        "子功能": "感觉刺激与调节模式",
        "应用名称": "小看戏",
        "应用路径": "flash/XC032.exe",
        "图标路径": "icons/APP032.png"
    },
    "APP033": {
        "领域": "感知觉统合",
        "子功能": "感觉刺激与调节模式",
        "应用名称": "跳圆舞曲的小猫",
        "应用路径": "flash/XC033.exe",
        "图标路径": "icons/APP033.png"
    },
    "APP034": {
        "领域": "感知觉统合",
        "子功能": "感觉刺激与调节模式",
        "应用名称": "春江花月夜",
        "应用路径": "flash/XC034.exe",
        "图标路径": "icons/APP034.png"
    },
    "APP035": {
        "领域": "感知觉统合",
        "子功能": "感觉刺激与调节模式",
        "应用名称": "魔术",
        "应用路径": "flash/XC035.exe",
        "图标路径": "icons/APP035.png"
    },
    "APP036": {
        "领域": "感知觉统合",
        "子功能": "感觉刺激与调节模式",
        "应用名称": "舞蹈",
        "应用路径": "flash/XC036.exe",
        "图标路径": "icons/APP036.png"
    },
    "APP037": {
        "领域": "感知觉统合",
        "子功能": "感觉刺激与调节模式",
        "应用名称": "孔雀舞",
        "应用路径": "flash/XC037.exe",
        "图标路径": "icons/APP037.png"
    },
    "APP038": {
        "领域": "感知觉统合",
        "子功能": "感觉刺激与调节模式",
        "应用名称": "大吊车",
        "应用路径": "flash/XC038.exe",
        "图标路径": "icons/APP038.png"
    },
    "APP039": {
        "领域": "感知觉统合",
        "子功能": "感觉刺激与调节模式",
        "应用名称": "山上一只虎",
        "应用路径": "flash/XC039.exe",
        "图标路径": "icons/APP039.png"
    },
    "APP040": {
        "领域": "感知觉统合",
        "子功能": "感觉刺激与调节模式",
        "应用名称": "拉德斯基进行曲",
        "应用路径": "flash/XC040.exe",
        "图标路径": "icons/APP040.png"
    },
    "APP041": {
        "领域": "感知觉统合",
        "子功能": "感觉刺激与调节模式",
        "应用名称": "快乐的啰嗦",
        "应用路径": "flash/XC041.exe",
        "图标路径": "icons/APP041.png"
    },
    "APP042": {
        "领域": "感知觉统合",
        "子功能": "感觉刺激与调节模式",
        "应用名称": "老师再见了",
        "应用路径": "flash/XC042.exe",
        "图标路径": "icons/APP042.png"
    },
    "APP043": {
        "领域": "感知觉统合",
        "子功能": "感觉刺激与调节模式",
        "应用名称": "星星二重唱",
        "应用路径": "flash/XC043.exe",
        "图标路径": "icons/APP043.png"
    },
    "APP044": {
        "领域": "感知觉统合",
        "子功能": "感觉刺激与调节模式",
        "应用名称": "春天来了",
        "应用路径": "flash/XC044.exe",
        "图标路径": "icons/APP044.png"
    },
    "APP045": {
        "领域": "感知觉统合",
        "子功能": "感觉刺激与调节模式",
        "应用名称": "梦之船",
        "应用路径": "flash/XC045.exe",
        "图标路径": "icons/APP045.png"
    },
    "APP046": {
        "领域": "感知觉统合",
        "子功能": "感觉刺激与调节模式",
        "应用名称": "魔法师的学徒",
        "应用路径": "flash/XC046.exe",
        "图标路径": "icons/APP046.png"
    },
    "APP047": {
        "领域": "感知觉统合",
        "子功能": "感觉刺激与调节模式",
        "应用名称": "春晓",
        "应用路径": "flash/XC047.exe",
        "图标路径": "icons/APP047.png"
    },
    "APP048": {
        "领域": "感知觉统合",
        "子功能": "感觉刺激与调节模式",
        "应用名称": "小篱笆",
        "应用路径": "flash/XC048.exe",
        "图标路径": "icons/APP048.png"
    },
    "APP049": {
        "领域": "感知觉统合",
        "子功能": "感觉刺激与调节模式",
        "应用名称": "快乐的小溪流",
        "应用路径": "flash/XC049.exe",
        "图标路径": "icons/APP049.png"
    },
    "APP050": {
        "领域": "感知觉统合",
        "子功能": "感觉刺激与调节模式",
        "应用名称": "小鸟小鸟",
        "应用路径": "flash/XC050.exe",
        "图标路径": "icons/APP050.png"
    },
    "APP051": {
        "领域": "感知觉统合",
        "子功能": "感觉刺激与调节模式",
        "应用名称": "半个月亮爬上来",
        "应用路径": "flash/XC051.exe",
        "图标路径": "icons/APP051.png"
    },
    "APP052": {
        "领域": "感知觉统合",
        "子功能": "感觉刺激与调节模式",
        "应用名称": "搏击舞",
        "应用路径": "flash/XC052.exe",
        "图标路径": "icons/APP052.png"
    },
    "APP053": {
        "领域": "感知觉统合",
        "子功能": "感觉刺激与调节模式",
        "应用名称": "悦宝兵团",
        "应用路径": "flash/XC053.exe",
        "图标路径": "icons/APP053.png"
    },
    "APP054": {
        "领域": "感知觉统合",
        "子功能": "感觉刺激与调节模式",
        "应用名称": "说唱脸谱",
        "应用路径": "flash/XC054.exe",
        "图标路径": "icons/APP054.png"
    },
    "APP055": {
        "领域": "感知觉统合",
        "子功能": "感觉刺激与调节模式",
        "应用名称": "划龙舟",
        "应用路径": "flash/XC055.exe",
        "图标路径": "icons/APP055.png"
    },
    "APP056": {
        "领域": "感知觉统合",
        "子功能": "感觉刺激与调节模式",
        "应用名称": "雷神进行曲",
        "应用路径": "flash/XC056.exe",
        "图标路径": "icons/APP056.png"
    },
    "APP057": {
        "领域": "感知觉统合",
        "子功能": "感觉刺激与调节模式",
        "应用名称": "快乐圆圈舞",
        "应用路径": "flash/XC057.exe",
        "图标路径": "icons/APP057.png"
    },
    "APP058": {
        "领域": "感知觉统合",
        "子功能": "感觉刺激与调节模式",
        "应用名称": "星球大战",
        "应用路径": "flash/XC058.exe",
        "图标路径": "icons/APP058.png"
    },
    "APP059": {
        "领域": "感知觉统合",
        "子功能": "视动整合模式",
        "应用名称": "小猫钓鱼",
        "应用路径": "flash/XC059.exe",
        "图标路径": "icons/APP059.png"
    },
    "APP060": {
        "领域": "感知觉统合",
        "子功能": "视动整合模式",
        "应用名称": "视觉画",
        "应用路径": "flash/XC060.exe",
        "图标路径": "icons/APP060.png"
    },
    "APP061": {
        "领域": "感知觉统合",
        "子功能": "视动整合模式",
        "应用名称": "拍画片",
        "应用路径": "flash/XC061.exe",
        "图标路径": "icons/APP061.png"
    },
    "APP062": {
        "领域": "感知觉统合",
        "子功能": "视动整合模式",
        "应用名称": "排排队",
        "应用路径": "flash/XC062.exe",
        "图标路径": "icons/APP062.png"
    },
    "APP063": {
        "领域": "感知觉统合",
        "子功能": "视动整合模式",
        "应用名称": "左右摇摆",
        "应用路径": "flash/XC063.exe",
        "图标路径": "icons/APP063.png"
    },
    "APP064": {
        "领域": "感知觉统合",
        "子功能": "视动整合模式",
        "应用名称": "桃花开",
        "应用路径": "flash/XC064.exe",
        "图标路径": "icons/APP064.png"
    },
    "APP065": {
        "领域": "感知觉统合",
        "子功能": "视动整合模式",
        "应用名称": "连环画设计师",
        "应用路径": "flash/XC065.exe",
        "图标路径": "icons/APP065.png"
    },
    "APP066": {
        "领域": "感知觉统合",
        "子功能": "视动整合模式",
        "应用名称": "画皮影",
        "应用路径": "flash/XC066.exe",
        "图标路径": "icons/APP066.png"
    },
    "APP067": {
        "领域": "感知觉统合",
        "子功能": "视动整合模式",
        "应用名称": "马蒂斯的花和草",
        "应用路径": "flash/XC067.exe",
        "图标路径": "icons/APP067.png"
    },
    "APP068": {
        "领域": "感知觉统合",
        "子功能": "视动整合模式",
        "应用名称": "剪羊毛",
        "应用路径": "flash/XC068.exe",
        "图标路径": "icons/APP068.png"
    },
    "APP069": {
        "领域": "感知觉统合",
        "子功能": "视动整合模式",
        "应用名称": "蛛网",
        "应用路径": "flash/XC069.exe",
        "图标路径": "icons/APP069.png"
    },
    "APP070": {
        "领域": "感知觉统合",
        "子功能": "视动整合模式",
        "应用名称": "春天的花帘",
        "应用路径": "flash/XC070.exe",
        "图标路径": "icons/APP070.png"
    },
    "APP071": {
        "领域": "感知觉统合",
        "子功能": "视动整合模式",
        "应用名称": "春暖花开",
        "应用路径": "flash/XC071.exe",
        "图标路径": "icons/APP071.png"
    },
    "APP072": {
        "领域": "感知觉统合",
        "子功能": "视动整合模式",
        "应用名称": "有趣的毛毛虫",
        "应用路径": "flash/XC072.exe",
        "图标路径": "icons/APP072.png"
    },
    "APP073": {
        "领域": "感知觉统合",
        "子功能": "视动整合模式",
        "应用名称": "七彩世界",
        "应用路径": "flash/XC073.exe",
        "图标路径": "icons/APP073.png"
    },
    "APP074": {
        "领域": "感知觉统合",
        "子功能": "视动整合模式",
        "应用名称": "奇妙的手形画",
        "应用路径": "flash/XC074.exe",
        "图标路径": "icons/APP074.png"
    },
    "APP075": {
        "领域": "感知觉统合",
        "子功能": "视动整合模式",
        "应用名称": "快乐染布",
        "应用路径": "flash/XC075.exe",
        "图标路径": "icons/APP075.png"
    },
    "APP076": {
        "领域": "感知觉统合",
        "子功能": "视动整合模式",
        "应用名称": "海底出击",
        "应用路径": "flash/XC076.exe",
        "图标路径": "icons/APP076.png"
    },
    "APP077": {
        "领域": "感知觉统合",
        "子功能": "视动整合模式",
        "应用名称": "春天在哪里",
        "应用路径": "flash/XC077.exe",
        "图标路径": "icons/APP077.png"
    },
    "APP078": {
        "领域": "感知觉统合",
        "子功能": "视动整合模式",
        "应用名称": "快乐乐园",
        "应用路径": "flash/XC078.exe",
        "图标路径": "icons/APP078.png"
    },
    "APP079": {
        "领域": "感知觉统合",
        "子功能": "视动整合模式",
        "应用名称": "一飞冲天",
        "应用路径": "flash/XC079.exe",
        "图标路径": "icons/APP079.png"
    },
    "APP080": {
        "领域": "感知觉统合",
        "子功能": "视动整合模式",
        "应用名称": "刀马旦",
        "应用路径": "flash/XC080.exe",
        "图标路径": "icons/APP080.png"
    },
    "APP081": {
        "领域": "感知觉统合",
        "子功能": "视动整合模式",
        "应用名称": "给妈妈的手袋",
        "应用路径": "flash/XC081.exe",
        "图标路径": "icons/APP081.png"
    },
    "APP082": {
        "领域": "感知觉统合",
        "子功能": "视动整合模式",
        "应用名称": "龙舟",
        "应用路径": "flash/XC082.exe",
        "图标路径": "icons/APP082.png"
    },
    "APP083": {
        "领域": "感知觉统合",
        "子功能": "艺术表达",
        "应用名称": "帽子",
        "应用路径": "flash/XC083.exe",
        "图标路径": "icons/APP083.png"
    },
    "APP084": {
        "领域": "感知觉统合",
        "子功能": "艺术表达",
        "应用名称": "花外衣",
        "应用路径": "flash/XC084.exe",
        "图标路径": "icons/APP084.png"
    },
    "APP085": {
        "领域": "感知觉统合",
        "子功能": "艺术表达",
        "应用名称": "兔兔",
        "应用路径": "flash/XC085.exe",
        "图标路径": "icons/APP085.png"
    },
    "APP086": {
        "领域": "感知觉统合",
        "子功能": "艺术表达",
        "应用名称": "甜甜的西瓜",
        "应用路径": "flash/XC086.exe",
        "图标路径": "icons/APP086.png"
    },
    "APP087": {
        "领域": "感知觉统合",
        "子功能": "艺术表达",
        "应用名称": "圈圈",
        "应用路径": "flash/XC087.exe",
        "图标路径": "icons/APP087.png"
    },
    "APP088": {
        "领域": "感知觉统合",
        "子功能": "艺术表达",
        "应用名称": "白天鹅",
        "应用路径": "flash/XC088.exe",
        "图标路径": "icons/APP088.png"
    },
    "APP089": {
        "领域": "感知觉统合",
        "子功能": "艺术表达",
        "应用名称": "青蛙先生",
        "应用路径": "flash/XC089.exe",
        "图标路径": "icons/APP089.png"
    },
    "APP090": {
        "领域": "感知觉统合",
        "子功能": "艺术表达",
        "应用名称": "你好，小怪兽",
        "应用路径": "flash/XC090.exe",
        "图标路径": "icons/APP090.png"
    },
    "APP091": {
        "领域": "感知觉统合",
        "子功能": "艺术表达",
        "应用名称": "旅行",
        "应用路径": "flash/XC091.exe",
        "图标路径": "icons/APP091.png"
    },
    "APP092": {
        "领域": "感知觉统合",
        "子功能": "艺术表达",
        "应用名称": "百变",
        "应用路径": "flash/XC092.exe",
        "图标路径": "icons/APP092.png"
    },
    "APP093": {
        "领域": "感知觉统合",
        "子功能": "艺术表达",
        "应用名称": "大鳄鱼",
        "应用路径": "flash/XC093.exe",
        "图标路径": "icons/APP093.png"
    },
    "APP094": {
        "领域": "感知觉统合",
        "子功能": "艺术表达",
        "应用名称": "好朋友，手拉手",
        "应用路径": "flash/XC094.exe",
        "图标路径": "icons/APP094.png"
    },
    "APP095": {
        "领域": "感知觉统合",
        "子功能": "艺术表达",
        "应用名称": "萤火虫",
        "应用路径": "flash/XC095.exe",
        "图标路径": "icons/APP095.png"
    },
    "APP096": {
        "领域": "感知觉统合",
        "子功能": "艺术表达",
        "应用名称": "我的自拍照",
        "应用路径": "flash/XC096.exe",
        "图标路径": "icons/APP096.png"
    },
    "APP097": {
        "领域": "感知觉统合",
        "子功能": "艺术表达",
        "应用名称": "粽意浓浓",
        "应用路径": "flash/XC370.exe",
        "图标路径": "icons/APP097.png"
    },
    "APP098": {
        "领域": "感知觉统合",
        "子功能": "艺术表达",
        "应用名称": "西瓜与葡萄",
        "应用路径": "flash/XC098.exe",
        "图标路径": "icons/APP098.png"
    },
    "APP099": {
        "领域": "感知觉统合",
        "子功能": "艺术表达",
        "应用名称": "采莲蓬",
        "应用路径": "flash/XC099.exe",
        "图标路径": "icons/APP099.png"
    },
    "APP100": {
        "领域": "感知觉统合",
        "子功能": "艺术表达",
        "应用名称": "鬼脸",
        "应用路径": "flash/XC100.exe",
        "图标路径": "icons/APP100.png"
    },
    "APP101": {
        "领域": "感知觉统合",
        "子功能": "艺术表达",
        "应用名称": "一家",
        "应用路径": "flash/XC101.exe",
        "图标路径": "icons/APP101.png"
    },
    "APP102": {
        "领域": "感知觉统合",
        "子功能": "艺术表达",
        "应用名称": "战胜大灰狼",
        "应用路径": "flash/XC102.exe",
        "图标路径": "icons/APP102.png"
    },
    "APP103": {
        "领域": "感知觉统合",
        "子功能": "艺术表达",
        "应用名称": "清凉扇",
        "应用路径": "flash/XC103.exe",
        "图标路径": "icons/APP103.png"
    },
    "APP104": {
        "领域": "感知觉统合",
        "子功能": "艺术表达",
        "应用名称": "水墨画",
        "应用路径": "flash/XC104.exe",
        "图标路径": "icons/APP104.png"
    },
    "APP105": {
        "领域": "感知觉统合",
        "子功能": "艺术表达",
        "应用名称": "草裙舞起来",
        "应用路径": "flash/XC105.exe",
        "图标路径": "icons/APP105.png"
    },
    "APP106": {
        "领域": "感知觉统合",
        "子功能": "艺术表达",
        "应用名称": "长大我",
        "应用路径": "flash/XC106.exe",
        "图标路径": "icons/APP106.png"
    },
    "APP107": {
        "领域": "感知觉统合",
        "子功能": "艺术表达",
        "应用名称": "佩香囊",
        "应用路径": "flash/XC372.exe",
        "图标路径": "icons/APP107.png"
    },
    "APP108": {
        "领域": "感知觉统合",
        "子功能": "艺术表达",
        "应用名称": "月亮上",
        "应用路径": "flash/XC373.exe",
        "图标路径": "icons/APP108.png"
    },
    "APP109": {
        "领域": "感知觉统合",
        "子功能": "艺术表达",
        "应用名称": "发明家",
        "应用路径": "flash/XC109.exe",
        "图标路径": "icons/APP109.png"
    },
    "APP110": {
        "领域": "感知觉统合",
        "子功能": "艺术表达",
        "应用名称": "幸福的大桌子",
        "应用路径": "flash/XC375.exe",
        "图标路径": "icons/APP110.png"
    },
    "APP111": {
        "领域": "感知觉统合",
        "子功能": "艺术表达",
        "应用名称": "我爱刷牙",
        "应用路径": "flash/XC111.exe",
        "图标路径": "icons/APP111.png"
    },
    "APP112": {
        "领域": "感知觉统合",
        "子功能": "艺术表达",
        "应用名称": "我的书包",
        "应用路径": "flash/XC358.exe",
        "图标路径": "icons/APP112.png"
    },
    "APP113": {
        "领域": "感知觉统合",
        "子功能": "艺术表达",
        "应用名称": "风筝",
        "应用路径": "flash/XC113.exe",
        "图标路径": "icons/APP113.png"
    },
    "APP114": {
        "领域": "感知觉统合",
        "子功能": "艺术表达",
        "应用名称": "屏风",
        "应用路径": "flash/XC114.exe",
        "图标路径": "icons/APP114.png"
    },
    "APP115": {
        "领域": "感知觉统合",
        "子功能": "艺术表达",
        "应用名称": "爸爸和我",
        "应用路径": "flash/XC115.exe",
        "图标路径": "icons/APP115.png"
    },
    "APP116": {
        "领域": "感知觉统合",
        "子功能": "艺术表达",
        "应用名称": "珍惜水资源",
        "应用路径": "flash/XC116.exe",
        "图标路径": "icons/APP116.png"
    },
    "APP117": {
        "领域": "感知觉统合",
        "子功能": "艺术表达",
        "应用名称": "丛林",
        "应用路径": "flash/XC117.exe",
        "图标路径": "icons/APP117.png"
    },
    "APP118": {
        "领域": "感知觉统合",
        "子功能": "艺术表达",
        "应用名称": "音乐会",
        "应用路径": "flash/XC118.exe",
        "图标路径": "icons/APP118.png"
    },
    "APP119": {
        "领域": "感知觉统合",
        "子功能": "艺术表达",
        "应用名称": "豪华巨轮",
        "应用路径": "flash/XC119.exe",
        "图标路径": "icons/APP119.png"
    },
    "APP120": {
        "领域": "感知觉统合",
        "子功能": "艺术表达",
        "应用名称": "遮阳帽",
        "应用路径": "flash/XC120.exe",
        "图标路径": "icons/APP120.png"
    },
    "APP121": {
        "领域": "执行功能",
        "子功能": "工作记忆强化",
        "应用名称": "5以内的点数",
        "应用路径": "flash/XC121.exe",
        "图标路径": "icons/APP121.png"
    },
    "APP122": {
        "领域": "执行功能",
        "子功能": "工作记忆强化",
        "应用名称": "20以内的点数",
        "应用路径": "flash/XC122.exe",
        "图标路径": "icons/APP122.png"
    },
    "APP123": {
        "领域": "执行功能",
        "子功能": "工作记忆强化",
        "应用名称": "20以内的数物结合",
        "应用路径": "flash/XC123.exe",
        "图标路径": "icons/APP123.png"
    },
    "APP124": {
        "领域": "执行功能",
        "子功能": "工作记忆强化",
        "应用名称": "认读50以内的数",
        "应用路径": "flash/XC124.exe",
        "图标路径": "icons/APP124.png"
    },
    "APP125": {
        "领域": "执行功能",
        "子功能": "工作记忆强化",
        "应用名称": "认识100以内的数",
        "应用路径": "flash/XC125.exe",
        "图标路径": "icons/APP125.png"
    },
    "APP126": {
        "领域": "执行功能",
        "子功能": "工作记忆强化",
        "应用名称": "认识100—1000的数",
        "应用路径": "flash/XC126.exe",
        "图标路径": "icons/APP126.png"
    },
    "APP127": {
        "领域": "执行功能",
        "子功能": "工作记忆强化",
        "应用名称": "复习10以内数的形成",
        "应用路径": "flash/XC127.exe",
        "图标路径": "icons/APP127.png"
    },
    "APP128": {
        "领域": "执行功能",
        "子功能": "工作记忆强化",
        "应用名称": "3的形成",
        "应用路径": "flash/XC128.exe",
        "图标路径": "icons/APP128.png"
    },
    "APP129": {
        "领域": "执行功能",
        "子功能": "工作记忆强化",
        "应用名称": "4、5的形成",
        "应用路径": "flash/XC129.exe",
        "图标路径": "icons/APP129.png"
    },
    "APP130": {
        "领域": "执行功能",
        "子功能": "工作记忆强化",
        "应用名称": "5的形成",
        "应用路径": "flash/XC130.exe",
        "图标路径": "icons/APP130.png"
    },
    "APP131": {
        "领域": "执行功能",
        "子功能": "工作记忆强化",
        "应用名称": "5以内的按数取物",
        "应用路径": "flash/XC131.exe",
        "图标路径": "icons/APP131.png"
    },
    "APP132": {
        "领域": "执行功能",
        "子功能": "工作记忆强化",
        "应用名称": "认识数字1、2、3",
        "应用路径": "flash/XC132.exe",
        "图标路径": "icons/APP132.png"
    },
    "APP133": {
        "领域": "执行功能",
        "子功能": "工作记忆强化",
        "应用名称": "认识数字4、5",
        "应用路径": "flash/XC133.exe",
        "图标路径": "icons/APP133.png"
    },
    "APP134": {
        "领域": "执行功能",
        "子功能": "序列指令",
        "应用名称": "复习10以内的序数",
        "应用路径": "flash/XC134.exe",
        "图标路径": "icons/APP134.png"
    },
    "APP135": {
        "领域": "执行功能",
        "子功能": "序列指令",
        "应用名称": "5以内的序数",
        "应用路径": "flash/XC135.exe",
        "图标路径": "icons/APP135.png"
    },
    "APP136": {
        "领域": "执行功能",
        "子功能": "序列指令",
        "应用名称": "认识单数、双数",
        "应用路径": "flash/XC136.exe",
        "图标路径": "icons/APP136.png"
    },
    "APP137": {
        "领域": "执行功能",
        "子功能": "序列指令",
        "应用名称": "相邻数1",
        "应用路径": "flash/XC137.exe",
        "图标路径": "icons/APP137.png"
    },
    "APP138": {
        "领域": "执行功能",
        "子功能": "序列指令",
        "应用名称": "相邻数2",
        "应用路径": "flash/XC138.exe",
        "图标路径": "icons/APP138.png"
    },
    "APP139": {
        "领域": "执行功能",
        "子功能": "序列指令",
        "应用名称": "10以内数的等差关系",
        "应用路径": "flash/XC139.exe",
        "图标路径": "icons/APP139.png"
    },
    "APP140": {
        "领域": "执行功能",
        "子功能": "序列指令",
        "应用名称": "目测数群（5、6、7）",
        "应用路径": "flash/XC140.exe",
        "图标路径": "icons/APP140.png"
    },
    "APP141": {
        "领域": "执行功能",
        "子功能": "序列指令",
        "应用名称": "目测数群（8、9、10）",
        "应用路径": "flash/XC141.exe",
        "图标路径": "icons/APP141.png"
    },
    "APP142": {
        "领域": "执行功能",
        "子功能": "序列指令",
        "应用名称": "按群计数（2、10）",
        "应用路径": "flash/XC142.exe",
        "图标路径": "icons/APP142.png"
    },
    "APP143": {
        "领域": "执行功能",
        "子功能": "序列指令",
        "应用名称": "按群计数（3、5）",
        "应用路径": "flash/XC143.exe",
        "图标路径": "icons/APP143.png"
    },
    "APP144": {
        "领域": "执行功能",
        "子功能": "序列指令",
        "应用名称": "个十百千",
        "应用路径": "flash/XC144.exe",
        "图标路径": "icons/APP144.png"
    },
    "APP145": {
        "领域": "执行功能",
        "子功能": "序列指令",
        "应用名称": "20以内的加减1",
        "应用路径": "flash/XC145.exe",
        "图标路径": "icons/APP145.png"
    },
    "APP146": {
        "领域": "执行功能",
        "子功能": "序列指令",
        "应用名称": "20以内的加减2",
        "应用路径": "flash/XC146.exe",
        "图标路径": "icons/APP146.png"
    },
    "APP147": {
        "领域": "执行功能",
        "子功能": "序列指令",
        "应用名称": "20以内加减列式计算",
        "应用路径": "flash/XC147.exe",
        "图标路径": "icons/APP147.png"
    },
    "APP148": {
        "领域": "执行功能",
        "子功能": "序列指令",
        "应用名称": "连加连减",
        "应用路径": "flash/XC148.exe",
        "图标路径": "icons/APP148.png"
    },
    "APP149": {
        "领域": "执行功能",
        "子功能": "多维度分类",
        "应用名称": "配对",
        "应用路径": "flash/XC149.exe",
        "图标路径": "icons/APP149.png"
    },
    "APP150": {
        "领域": "执行功能",
        "子功能": "多维度分类",
        "应用名称": "特征分类",
        "应用路径": "flash/XC150.exe",
        "图标路径": "icons/APP150.png"
    },
    "APP151": {
        "领域": "执行功能",
        "子功能": "多维度分类",
        "应用名称": "分类属性",
        "应用路径": "flash/XC151.exe",
        "图标路径": "icons/APP151.png"
    },
    "APP152": {
        "领域": "执行功能",
        "子功能": "多维度分类",
        "应用名称": "多重特征分类",
        "应用路径": "flash/XC152.exe",
        "图标路径": "icons/APP152.png"
    },
    "APP153": {
        "领域": "执行功能",
        "子功能": "多维度分类",
        "应用名称": "按两种特征分类2",
        "应用路径": "flash/XC153.exe",
        "图标路径": "icons/APP153.png"
    },
    "APP154": {
        "领域": "执行功能",
        "子功能": "多维度分类",
        "应用名称": "多级别分类",
        "应用路径": "flash/XC154.exe",
        "图标路径": "icons/APP154.png"
    },
    "APP155": {
        "领域": "执行功能",
        "子功能": "多维度分类",
        "应用名称": "混合分类",
        "应用路径": "flash/XC155.exe",
        "图标路径": "icons/APP155.png"
    },
    "APP156": {
        "领域": "执行功能",
        "子功能": "多维度分类",
        "应用名称": "二维、三维分类，标识分类",
        "应用路径": "flash/XC156.exe",
        "图标路径": "icons/APP156.png"
    },
    "APP157": {
        "领域": "执行功能",
        "子功能": "多维度分类",
        "应用名称": "复习子集、交集、差集",
        "应用路径": "flash/XC157.exe",
        "图标路径": "icons/APP157.png"
    },
    "APP158": {
        "领域": "执行功能",
        "子功能": "规律转换",
        "应用名称": "寻找排序规律",
        "应用路径": "flash/XC158.exe",
        "图标路径": "icons/APP158.png"
    },
    "APP159": {
        "领域": "执行功能",
        "子功能": "规律转换",
        "应用名称": "排序的特征",
        "应用路径": "flash/XC159.exe",
        "图标路径": "icons/APP159.png"
    },
    "APP160": {
        "领域": "执行功能",
        "子功能": "规律转换",
        "应用名称": "排列",
        "应用路径": "flash/XC160.exe",
        "图标路径": "icons/APP160.png"
    },
    "APP161": {
        "领域": "执行功能",
        "子功能": "规律转换",
        "应用名称": "多重排列",
        "应用路径": "flash/XC161.exe",
        "图标路径": "icons/APP161.png"
    },
    "APP162": {
        "领域": "执行功能",
        "子功能": "规律转换",
        "应用名称": "二维排列",
        "应用路径": "flash/XC162.exe",
        "图标路径": "icons/APP162.png"
    },
    "APP163": {
        "领域": "执行功能",
        "子功能": "规律转换",
        "应用名称": "排序描述",
        "应用路径": "flash/XC163.exe",
        "图标路径": "icons/APP163.png"
    },
    "APP164": {
        "领域": "执行功能",
        "子功能": "规律转换",
        "应用名称": "量的变化",
        "应用路径": "flash/XC164.exe",
        "图标路径": "icons/APP164.png"
    },
    "APP165": {
        "领域": "执行功能",
        "子功能": "规律转换",
        "应用名称": "量的推理",
        "应用路径": "flash/XC165.exe",
        "图标路径": "icons/APP165.png"
    },
    "APP166": {
        "领域": "执行功能",
        "子功能": "规律转换",
        "应用名称": "分类数数",
        "应用路径": "flash/XC166.exe",
        "图标路径": "icons/APP166.png"
    },
    "APP167": {
        "领域": "执行功能",
        "子功能": "规律转换",
        "应用名称": "体积、容积守恒",
        "应用路径": "flash/XC167.exe",
        "图标路径": "icons/APP167.png"
    },
    "APP168": {
        "领域": "执行功能",
        "子功能": "图形策略",
        "应用名称": "高矮",
        "应用路径": "flash/XC168.exe",
        "图标路径": "icons/APP168.png"
    },
    "APP169": {
        "领域": "执行功能",
        "子功能": "图形策略",
        "应用名称": "里和外",
        "应用路径": "flash/XC169.exe",
        "图标路径": "icons/APP169.png"
    },
    "APP170": {
        "领域": "执行功能",
        "子功能": "图形策略",
        "应用名称": "远近",
        "应用路径": "flash/XC170.exe",
        "图标路径": "icons/APP170.png"
    },
    "APP171": {
        "领域": "执行功能",
        "子功能": "图形策略",
        "应用名称": "图形",
        "应用路径": "flash/XC171.exe",
        "图标路径": "icons/APP171.png"
    },
    "APP172": {
        "领域": "执行功能",
        "子功能": "图形策略",
        "应用名称": "菱形",
        "应用路径": "flash/XC172.exe",
        "图标路径": "icons/APP172.png"
    },
    "APP173": {
        "领域": "执行功能",
        "子功能": "图形策略",
        "应用名称": "空间分割",
        "应用路径": "flash/XC173.exe",
        "图标路径": "icons/APP173.png"
    },
    "APP174": {
        "领域": "执行功能",
        "子功能": "图形策略",
        "应用名称": "空间组合",
        "应用路径": "flash/XC174.exe",
        "图标路径": "icons/APP174.png"
    },
    "APP175": {
        "领域": "执行功能",
        "子功能": "图形策略",
        "应用名称": "空间拼接",
        "应用路径": "flash/XC175.exe",
        "图标路径": "icons/APP175.png"
    },
    "APP176": {
        "领域": "执行功能",
        "子功能": "图形策略",
        "应用名称": "重叠",
        "应用路径": "flash/XC176.exe",
        "图标路径": "icons/APP176.png"
    },
    "APP177": {
        "领域": "执行功能",
        "子功能": "图形策略",
        "应用名称": "二等分、四等分",
        "应用路径": "flash/XC177.exe",
        "图标路径": "icons/APP177.png"
    },
    "APP178": {
        "领域": "执行功能",
        "子功能": "图形策略",
        "应用名称": "认识轴对称和中心对称",
        "应用路径": "flash/XC178.exe",
        "图标路径": "icons/APP178.png"
    },
    "APP179": {
        "领域": "执行功能",
        "子功能": "图形策略",
        "应用名称": "等分",
        "应用路径": "flash/XC179.exe",
        "图标路径": "icons/APP179.png"
    },
    "APP180": {
        "领域": "执行功能",
        "子功能": "图形策略",
        "应用名称": "空间对称",
        "应用路径": "flash/XC180.exe",
        "图标路径": "icons/APP180.png"
    },
    "APP181": {
        "领域": "执行功能",
        "子功能": "图形策略",
        "应用名称": "图形的遮挡",
        "应用路径": "flash/XC181.exe",
        "图标路径": "icons/APP181.png"
    },
    "APP182": {
        "领域": "执行功能",
        "子功能": "图形策略",
        "应用名称": "三角形和正方形组合",
        "应用路径": "flash/XC182.exe",
        "图标路径": "icons/APP182.png"
    },
    "APP183": {
        "领域": "执行功能",
        "子功能": "图形策略",
        "应用名称": "正方形和长方形组合",
        "应用路径": "flash/XC183.exe",
        "图标路径": "icons/APP183.png"
    },
    "APP184": {
        "领域": "执行功能",
        "子功能": "问题解决",
        "应用名称": "平均分配1",
        "应用路径": "flash/XC184.exe",
        "图标路径": "icons/APP184.png"
    },
    "APP185": {
        "领域": "执行功能",
        "子功能": "问题解决",
        "应用名称": "平均分配2",
        "应用路径": "flash/XC185.exe",
        "图标路径": "icons/APP185.png"
    },
    "APP186": {
        "领域": "执行功能",
        "子功能": "问题解决",
        "应用名称": "分配",
        "应用路径": "flash/XC186.exe",
        "图标路径": "icons/APP186.png"
    },
    "APP187": {
        "领域": "执行功能",
        "子功能": "问题解决",
        "应用名称": "大于和小于",
        "应用路径": "flash/XC187.exe",
        "图标路径": "icons/APP187.png"
    },
    "APP188": {
        "领域": "执行功能",
        "子功能": "问题解决",
        "应用名称": "复习10以内的加减法",
        "应用路径": "flash/XC188.exe",
        "图标路径": "icons/APP188.png"
    },
    "APP189": {
        "领域": "执行功能",
        "子功能": "问题解决",
        "应用名称": "整10加、整10减",
        "应用路径": "flash/XC189.exe",
        "图标路径": "icons/APP189.png"
    },
    "APP190": {
        "领域": "执行功能",
        "子功能": "问题解决",
        "应用名称": "整5加、整5减",
        "应用路径": "flash/XC190.exe",
        "图标路径": "icons/APP190.png"
    },
    "APP191": {
        "领域": "执行功能",
        "子功能": "问题解决",
        "应用名称": "20以内自编应用题",
        "应用路径": "flash/XC191.exe",
        "图标路径": "icons/APP191.png"
    },
    "APP192": {
        "领域": "执行功能",
        "子功能": "问题解决",
        "应用名称": "20以内连加连减应用题",
        "应用路径": "flash/XC192.exe",
        "图标路径": "icons/APP192.png"
    },
    "APP193": {
        "领域": "执行功能",
        "子功能": "问题解决",
        "应用名称": "等量代换",
        "应用路径": "flash/XC193.exe",
        "图标路径": "icons/APP193.png"
    },
    "APP194": {
        "领域": "社交沟通",
        "子功能": "心智解读",
        "应用名称": "节日",
        "应用路径": "flash/XC194.exe",
        "图标路径": "icons/APP194.png"
    },
    "APP195": {
        "领域": "社交沟通",
        "子功能": "心智解读",
        "应用名称": "不摘花",
        "应用路径": "flash/XC195.exe",
        "图标路径": "icons/APP195.png"
    },
    "APP196": {
        "领域": "社交沟通",
        "子功能": "心智解读",
        "应用名称": "生气了",
        "应用路径": "flash/XC196.exe",
        "图标路径": "icons/APP196.png"
    },
    "APP197": {
        "领域": "社交沟通",
        "子功能": "心智解读",
        "应用名称": "走丢",
        "应用路径": "flash/XC322.exe",
        "图标路径": "icons/APP197.png"
    },
    "APP198": {
        "领域": "社交沟通",
        "子功能": "心智解读",
        "应用名称": "小猪的新房子",
        "应用路径": "flash/XC198.exe",
        "图标路径": "icons/APP198.png"
    },
    "APP199": {
        "领域": "社交沟通",
        "子功能": "心智解读",
        "应用名称": "轻轻地，不打扰",
        "应用路径": "flash/XC401.exe",
        "图标路径": "icons/APP199.png"
    },
    "APP200": {
        "领域": "社交沟通",
        "子功能": "心智解读",
        "应用名称": "衣服",
        "应用路径": "flash/XC200.exe",
        "图标路径": "icons/APP200.png"
    },
    "APP201": {
        "领域": "社交沟通",
        "子功能": "心智解读",
        "应用名称": "小眼睛",
        "应用路径": "flash/XC403.exe",
        "图标路径": "icons/APP201.png"
    },
    "APP202": {
        "领域": "社交沟通",
        "子功能": "心智解读",
        "应用名称": "礼貌",
        "应用路径": "flash/XC202.exe",
        "图标路径": "icons/APP202.png"
    },
    "APP203": {
        "领域": "社交沟通",
        "子功能": "心智解读",
        "应用名称": "玩具小鸭要回家",
        "应用路径": "flash/XC404.exe",
        "图标路径": "icons/APP203.png"
    },
    "APP204": {
        "领域": "社交沟通",
        "子功能": "心智解读",
        "应用名称": "做客",
        "应用路径": "flash/XC204.exe",
        "图标路径": "icons/APP204.png"
    },
    "APP205": {
        "领域": "社交沟通",
        "子功能": "心智解读",
        "应用名称": "会咬人的电",
        "应用路径": "flash/XC205.exe",
        "图标路径": "icons/APP205.png"
    },
    "APP206": {
        "领域": "社交沟通",
        "子功能": "心智解读",
        "应用名称": "快乐",
        "应用路径": "flash/XC377.exe",
        "图标路径": "icons/APP206.png"
    },
    "APP207": {
        "领域": "社交沟通",
        "子功能": "心智解读",
        "应用名称": "上街去",
        "应用路径": "flash/XC207.exe",
        "图标路径": "icons/APP207.png"
    },
    "APP208": {
        "领域": "社交沟通",
        "子功能": "心智解读",
        "应用名称": "身边的危险",
        "应用路径": "flash/XC208.exe",
        "图标路径": "icons/APP208.png"
    },
    "APP209": {
        "领域": "社交沟通",
        "子功能": "心智解读",
        "应用名称": "我长大了",
        "应用路径": "flash/XC407.exe",
        "图标路径": "icons/APP209.png"
    },
    "APP210": {
        "领域": "社交沟通",
        "子功能": "心智解读",
        "应用名称": "好伙伴",
        "应用路径": "flash/XC210.exe",
        "图标路径": "icons/APP210.png"
    },
    "APP211": {
        "领域": "社交沟通",
        "子功能": "心智解读",
        "应用名称": "我和大树做朋友",
        "应用路径": "flash/XC211.exe",
        "图标路径": "icons/APP211.png"
    },
    "APP212": {
        "领域": "社交沟通",
        "子功能": "心智解读",
        "应用名称": "浪费不应该",
        "应用路径": "flash/XC408.exe",
        "图标路径": "icons/APP212.png"
    },
    "APP213": {
        "领域": "社交沟通",
        "子功能": "心智解读",
        "应用名称": "不乱吃东西",
        "应用路径": "flash/XC400.exe",
        "图标路径": "icons/APP213.png"
    },
    "APP214": {
        "领域": "社交沟通",
        "子功能": "心智解读",
        "应用名称": "我是快乐的孩子",
        "应用路径": "flash/XC214.exe",
        "图标路径": "icons/APP214.png"
    },
    "APP215": {
        "领域": "社交沟通",
        "子功能": "心智解读",
        "应用名称": "狼来了",
        "应用路径": "flash/XC215.exe",
        "图标路径": "icons/APP215.png"
    },
    "APP216": {
        "领域": "社交沟通",
        "子功能": "心智解读",
        "应用名称": "大熊的拥抱节",
        "应用路径": "flash/XC216.exe",
        "图标路径": "icons/APP216.png"
    },
    "APP217": {
        "领域": "社交沟通",
        "子功能": "心智解读",
        "应用名称": "去看病",
        "应用路径": "flash/XC217.exe",
        "图标路径": "icons/APP217.png"
    },
    "APP218": {
        "领域": "社交沟通",
        "子功能": "心智解读",
        "应用名称": "我不怕",
        "应用路径": "flash/XC218.exe",
        "图标路径": "icons/APP218.png"
    },
    "APP219": {
        "领域": "社交沟通",
        "子功能": "心智解读",
        "应用名称": "妈妈辛苦了",
        "应用路径": "flash/XC219.exe",
        "图标路径": "icons/APP219.png"
    },
    "APP220": {
        "领域": "社交沟通",
        "子功能": "心智解读",
        "应用名称": "有趣的筷子",
        "应用路径": "flash/XC409.exe",
        "图标路径": "icons/APP220.png"
    },
    "APP221": {
        "领域": "社交沟通",
        "子功能": "心智解读",
        "应用名称": "会说话的标识",
        "应用路径": "flash/XC405.exe",
        "图标路径": "icons/APP221.png"
    },
    "APP222": {
        "领域": "社交沟通",
        "子功能": "心智解读",
        "应用名称": "风娃娃的心愿",
        "应用路径": "flash/XC406.exe",
        "图标路径": "icons/APP222.png"
    },
    "APP223": {
        "领域": "社交沟通",
        "子功能": "心智解读",
        "应用名称": "我喜欢我",
        "应用路径": "flash/XC223.exe",
        "图标路径": "icons/APP223.png"
    },
    "APP224": {
        "领域": "社交沟通",
        "子功能": "心智解读",
        "应用名称": "游泳真快乐",
        "应用路径": "flash/XC224.exe",
        "图标路径": "icons/APP224.png"
    },
    "APP225": {
        "领域": "社交沟通",
        "子功能": "心智解读",
        "应用名称": "文明小乘客",
        "应用路径": "flash/XC411.exe",
        "图标路径": "icons/APP225.png"
    },
    "APP226": {
        "领域": "社交沟通",
        "子功能": "心智解读",
        "应用名称": "小小志愿者",
        "应用路径": "flash/XC226.exe",
        "图标路径": "icons/APP226.png"
    },
    "APP227": {
        "领域": "社交沟通",
        "子功能": "心智解读",
        "应用名称": "植树节",
        "应用路径": "flash/XC364.exe",
        "图标路径": "icons/APP227.png"
    },
    "APP228": {
        "领域": "社交沟通",
        "子功能": "心智解读",
        "应用名称": "有趣的生肖",
        "应用路径": "flash/XC228.exe",
        "图标路径": "icons/APP228.png"
    },
    "APP229": {
        "领域": "社交沟通",
        "子功能": "心智解读",
        "应用名称": "有害的烟雾",
        "应用路径": "flash/XC412.exe",
        "图标路径": "icons/APP229.png"
    },
    "APP230": {
        "领域": "社交沟通",
        "子功能": "心智解读",
        "应用名称": "中餐和西餐",
        "应用路径": "flash/XC230.exe",
        "图标路径": "icons/APP230.png"
    },
    "APP231": {
        "领域": "社交沟通",
        "子功能": "心智解读",
        "应用名称": "在公共场所",
        "应用路径": "flash/XC413.exe",
        "图标路径": "icons/APP231.png"
    },
    "APP232": {
        "领域": "社交沟通",
        "子功能": "心智解读",
        "应用名称": "我该怎么办",
        "应用路径": "flash/XC414.exe",
        "图标路径": "icons/APP232.png"
    },
    "APP233": {
        "领域": "社交沟通",
        "子功能": "心智解读",
        "应用名称": "国粹京韵",
        "应用路径": "flash/XC233.exe",
        "图标路径": "icons/APP233.png"
    },
    "APP234": {
        "领域": "社交沟通",
        "子功能": "心智解读",
        "应用名称": "您辛苦了",
        "应用路径": "flash/XC382.exe",
        "图标路径": "icons/APP234.png"
    },
    "APP235": {
        "领域": "社交沟通",
        "子功能": "心智解读",
        "应用名称": "约定",
        "应用路径": "flash/XC383.exe",
        "图标路径": "icons/APP235.png"
    },
    "APP236": {
        "领域": "社交沟通",
        "子功能": "心智解读",
        "应用名称": "神奇的书信",
        "应用路径": "flash/XC236.exe",
        "图标路径": "icons/APP236.png"
    },
    "APP237": {
        "领域": "社交沟通",
        "子功能": "心智解读",
        "应用名称": "蚂蚁搬豆",
        "应用路径": "flash/XC415.exe",
        "图标路径": "icons/APP237.png"
    },
    "APP238": {
        "领域": "社交沟通",
        "子功能": "心智解读",
        "应用名称": "暴雨来了",
        "应用路径": "flash/XC326.exe",
        "图标路径": "icons/APP238.png"
    },
    "APP239": {
        "领域": "社交沟通",
        "子功能": "心智解读",
        "应用名称": "端午节",
        "应用路径": "flash/XC371.exe",
        "图标路径": "icons/APP239.png"
    },
    "APP240": {
        "领域": "社交沟通",
        "子功能": "心智解读",
        "应用名称": "爸爸的大手",
        "应用路径": "flash/XC384.exe",
        "图标路径": "icons/APP240.png"
    },
    "APP241": {
        "领域": "社交沟通",
        "子功能": "心智解读",
        "应用名称": "我要上小学",
        "应用路径": "flash/XC385.exe",
        "图标路径": "icons/APP241.png"
    },
    "APP242": {
        "领域": "社交沟通",
        "子功能": "心智解读",
        "应用名称": "守时的孩子",
        "应用路径": "flash/XC417.exe",
        "图标路径": "icons/APP242.png"
    },
    "APP243": {
        "领域": "社交沟通",
        "子功能": "心智解读",
        "应用名称": "光盘行动",
        "应用路径": "flash/XC418.exe",
        "图标路径": "icons/APP243.png"
    },
    "APP244": {
        "领域": "社交沟通",
        "子功能": "心智解读",
        "应用名称": "学会等待",
        "应用路径": "flash/XC386.exe",
        "图标路径": "icons/APP244.png"
    },
    "APP245": {
        "领域": "社交沟通",
        "子功能": "心智解读",
        "应用名称": "有趣的节日",
        "应用路径": "flash/XC367.exe",
        "图标路径": "icons/APP245.png"
    },
    "APP246": {
        "领域": "社交沟通",
        "子功能": "心智解读",
        "应用名称": "汉字像幅画",
        "应用路径": "flash/XC368.exe",
        "图标路径": "icons/APP246.png"
    },
    "APP247": {
        "领域": "社交沟通",
        "子功能": "心智解读",
        "应用名称": "世界真精彩",
        "应用路径": "flash/XC369.exe",
        "图标路径": "icons/APP247.png"
    },
    "APP248": {
        "领域": "社交沟通",
        "子功能": "心智解读",
        "应用名称": "身边的广告",
        "应用路径": "flash/XC248.exe",
        "图标路径": "icons/APP248.png"
    },
    "APP249": {
        "领域": "社交沟通",
        "子功能": "心智解读",
        "应用名称": "坚持",
        "应用路径": "flash/XC387.exe",
        "图标路径": "icons/APP249.png"
    },
    "APP250": {
        "领域": "社交沟通",
        "子功能": "心智解读",
        "应用名称": "不贪心",
        "应用路径": "flash/XC388.exe",
        "图标路径": "icons/APP250.png"
    },
    "APP251": {
        "领域": "社交沟通",
        "子功能": "心智解读",
        "应用名称": "小鬼当家",
        "应用路径": "flash/XC251.exe",
        "图标路径": "icons/APP251.png"
    },
    "APP252": {
        "领域": "社交沟通",
        "子功能": "心智解读",
        "应用名称": "小书包",
        "应用路径": "flash/XC354.exe",
        "图标路径": "icons/APP252.png"
    },
    "APP253": {
        "领域": "社交沟通",
        "子功能": "心智解读",
        "应用名称": "课间十分钟",
        "应用路径": "flash/XC355.exe",
        "图标路径": "icons/APP253.png"
    },
    "APP254": {
        "领域": "社交沟通",
        "子功能": "心智解读",
        "应用名称": "离园倒计时",
        "应用路径": "flash/XC389.exe",
        "图标路径": "icons/APP254.png"
    },
    "APP255": {
        "领域": "社交沟通",
        "子功能": "心智解读",
        "应用名称": "毕业典礼",
        "应用路径": "flash/XC390.exe",
        "图标路径": "icons/APP255.png"
    },
    "APP256": {
        "领域": "社交沟通",
        "子功能": "心智解读",
        "应用名称": "不攀比",
        "应用路径": "flash/XC391.exe",
        "图标路径": "icons/APP256.png"
    },
    "APP257": {
        "领域": "社交沟通",
        "子功能": "心智解读",
        "应用名称": "谦让",
        "应用路径": "flash/XC257.exe",
        "图标路径": "icons/APP257.png"
    },
    "APP258": {
        "领域": "社交沟通",
        "子功能": "规则内化",
        "应用名称": "鼾声",
        "应用路径": "flash/XC258.exe",
        "图标路径": "icons/APP258.png"
    },
    "APP259": {
        "领域": "社交沟通",
        "子功能": "规则内化",
        "应用名称": "狐狸",
        "应用路径": "flash/XC259.exe",
        "图标路径": "icons/APP259.png"
    },
    "APP260": {
        "领域": "社交沟通",
        "子功能": "规则内化",
        "应用名称": "新房",
        "应用路径": "flash/XC260.exe",
        "图标路径": "icons/APP260.png"
    },
    "APP261": {
        "领域": "社交沟通",
        "子功能": "规则内化",
        "应用名称": "九九歌",
        "应用路径": "flash/XC261.exe",
        "图标路径": "icons/APP261.png"
    },
    "APP262": {
        "领域": "社交沟通",
        "子功能": "规则内化",
        "应用名称": "勇敢",
        "应用路径": "flash/XC393.exe",
        "图标路径": "icons/APP262.png"
    },
    "APP263": {
        "领域": "社交沟通",
        "子功能": "规则内化",
        "应用名称": "哪吒闹海",
        "应用路径": "flash/XC263.exe",
        "图标路径": "icons/APP263.png"
    },
    "APP264": {
        "领域": "社交沟通",
        "子功能": "规则内化",
        "应用名称": "寒号鸟",
        "应用路径": "flash/XC264.exe",
        "图标路径": "icons/APP264.png"
    },
    "APP265": {
        "领域": "社交沟通",
        "子功能": "规则内化",
        "应用名称": "借尾巴",
        "应用路径": "flash/XC265.exe",
        "图标路径": "icons/APP265.png"
    },
    "APP266": {
        "领域": "社交沟通",
        "子功能": "规则内化",
        "应用名称": "尾巴歌",
        "应用路径": "flash/XC266.exe",
        "图标路径": "icons/APP266.png"
    },
    "APP267": {
        "领域": "社交沟通",
        "子功能": "规则内化",
        "应用名称": "好朋友",
        "应用路径": "flash/XC267.exe",
        "图标路径": "icons/APP267.png"
    },
    "APP268": {
        "领域": "社交沟通",
        "子功能": "规则内化",
        "应用名称": "星星和萤火虫",
        "应用路径": "flash/XC268.exe",
        "图标路径": "icons/APP268.png"
    },
    "APP269": {
        "领域": "社交沟通",
        "子功能": "规则内化",
        "应用名称": "晒太阳",
        "应用路径": "flash/XC269.exe",
        "图标路径": "icons/APP269.png"
    },
    "APP270": {
        "领域": "社交沟通",
        "子功能": "规则内化",
        "应用名称": "晚安",
        "应用路径": "flash/XC270.exe",
        "图标路径": "icons/APP270.png"
    },
    "APP271": {
        "领域": "社交沟通",
        "子功能": "规则内化",
        "应用名称": "没见过太阳的蚯蚓",
        "应用路径": "flash/XC271.exe",
        "图标路径": "icons/APP271.png"
    },
    "APP272": {
        "领域": "社交沟通",
        "子功能": "规则内化",
        "应用名称": "睡觉",
        "应用路径": "flash/XC272.exe",
        "图标路径": "icons/APP272.png"
    },
    "APP273": {
        "领域": "社交沟通",
        "子功能": "规则内化",
        "应用名称": "老鼠嫁女",
        "应用路径": "flash/XC273.exe",
        "图标路径": "icons/APP273.png"
    },
    "APP274": {
        "领域": "社交沟通",
        "子功能": "规则内化",
        "应用名称": "老鼠抬花轿",
        "应用路径": "flash/XC274.exe",
        "图标路径": "icons/APP274.png"
    },
    "APP275": {
        "领域": "社交沟通",
        "子功能": "规则内化",
        "应用名称": "萤火虫和小麻雀",
        "应用路径": "flash/XC275.exe",
        "图标路径": "icons/APP275.png"
    },
    "APP276": {
        "领域": "社交沟通",
        "子功能": "规则内化",
        "应用名称": "蜥蜴和老砖墙",
        "应用路径": "flash/XC276.exe",
        "图标路径": "icons/APP276.png"
    },
    "APP277": {
        "领域": "社交沟通",
        "子功能": "规则内化",
        "应用名称": "商店",
        "应用路径": "flash/XC277.exe",
        "图标路径": "icons/APP277.png"
    },
    "APP278": {
        "领域": "社交沟通",
        "子功能": "规则内化",
        "应用名称": "石头",
        "应用路径": "flash/XC278.exe",
        "图标路径": "icons/APP278.png"
    },
    "APP279": {
        "领域": "社交沟通",
        "子功能": "互动启发",
        "应用名称": "大苹果",
        "应用路径": "flash/XC279.exe",
        "图标路径": "icons/APP279.png"
    },
    "APP280": {
        "领域": "社交沟通",
        "子功能": "互动启发",
        "应用名称": "丑小鸭",
        "应用路径": "flash/XC280.exe",
        "图标路径": "icons/APP280.png"
    },
    "APP281": {
        "领域": "社交沟通",
        "子功能": "互动启发",
        "应用名称": "倒映",
        "应用路径": "flash/XC281.exe",
        "图标路径": "icons/APP281.png"
    },
    "APP282": {
        "领域": "社交沟通",
        "子功能": "互动启发",
        "应用名称": "大苹果儿歌",
        "应用路径": "flash/XC282.exe",
        "图标路径": "icons/APP282.png"
    },
    "APP283": {
        "领域": "社交沟通",
        "子功能": "互动启发",
        "应用名称": "要是发烧了",
        "应用路径": "flash/XC283.exe",
        "图标路径": "icons/APP283.png"
    },
    "APP284": {
        "领域": "社交沟通",
        "子功能": "互动启发",
        "应用名称": "孙悟空大战牛魔王",
        "应用路径": "flash/XC284.exe",
        "图标路径": "icons/APP284.png"
    },
    "APP285": {
        "领域": "社交沟通",
        "子功能": "互动启发",
        "应用名称": "月亮",
        "应用路径": "flash/XC285.exe",
        "图标路径": "icons/APP285.png"
    },
    "APP286": {
        "领域": "社交沟通",
        "子功能": "互动启发",
        "应用名称": "蘑菇",
        "应用路径": "flash/XC286.exe",
        "图标路径": "icons/APP286.png"
    },
    "APP287": {
        "领域": "社交沟通",
        "子功能": "互动启发",
        "应用名称": "房子",
        "应用路径": "flash/XC287.exe",
        "图标路径": "icons/APP287.png"
    },
    "APP288": {
        "领域": "社交沟通",
        "子功能": "互动启发",
        "应用名称": "手指",
        "应用路径": "flash/XC288.exe",
        "图标路径": "icons/APP288.png"
    },
    "APP289": {
        "领域": "社交沟通",
        "子功能": "互动启发",
        "应用名称": "喷嚏",
        "应用路径": "flash/XC289.exe",
        "图标路径": "icons/APP289.png"
    },
    "APP290": {
        "领域": "社交沟通",
        "子功能": "互动启发",
        "应用名称": "火鸡和鳄鱼",
        "应用路径": "flash/XC290.exe",
        "图标路径": "icons/APP290.png"
    },
    "APP291": {
        "领域": "社交沟通",
        "子功能": "互动启发",
        "应用名称": "老爸",
        "应用路径": "flash/XC291.exe",
        "图标路径": "icons/APP291.png"
    },
    "APP292": {
        "领域": "社交沟通",
        "子功能": "互动启发",
        "应用名称": "树",
        "应用路径": "flash/XC292.exe",
        "图标路径": "icons/APP292.png"
    },
    "APP293": {
        "领域": "社交沟通",
        "子功能": "互动启发",
        "应用名称": "雪糕",
        "应用路径": "flash/XC293.exe",
        "图标路径": "icons/APP293.png"
    },
    "APP294": {
        "领域": "社交沟通",
        "子功能": "互动启发",
        "应用名称": "喜欢毛茸茸",
        "应用路径": "flash/XC294.exe",
        "图标路径": "icons/APP294.png"
    },
    "APP295": {
        "领域": "社交沟通",
        "子功能": "互动启发",
        "应用名称": "城里老鼠和乡下老鼠",
        "应用路径": "flash/XC295.exe",
        "图标路径": "icons/APP295.png"
    },
    "APP296": {
        "领域": "社交沟通",
        "子功能": "互动启发",
        "应用名称": "小熊砍树",
        "应用路径": "flash/XC296.exe",
        "图标路径": "icons/APP296.png"
    },
    "APP297": {
        "领域": "社交沟通",
        "子功能": "互动启发",
        "应用名称": "理想",
        "应用路径": "flash/XC297.exe",
        "图标路径": "icons/APP297.png"
    },
    "APP298": {
        "领域": "社交沟通",
        "子功能": "互动启发",
        "应用名称": "梦想",
        "应用路径": "flash/XC298.exe",
        "图标路径": "icons/APP298.png"
    },
    "APP299": {
        "领域": "社交沟通",
        "子功能": "互动启发",
        "应用名称": "梦想成真之夜",
        "应用路径": "flash/XC396.exe",
        "图标路径": "icons/APP299.png"
    },
    "APP300": {
        "领域": "社交沟通",
        "子功能": "互动启发",
        "应用名称": "猜谜语",
        "应用路径": "flash/XC300.exe",
        "图标路径": "icons/APP300.png"
    },
    "APP301": {
        "领域": "社交沟通",
        "子功能": "互动启发",
        "应用名称": "猪八戒吃西瓜",
        "应用路径": "flash/XC301.exe",
        "图标路径": "icons/APP301.png"
    },
    "APP302": {
        "领域": "社交沟通",
        "子功能": "互动启发",
        "应用名称": "猪八戒嘴巴长",
        "应用路径": "flash/XC302.exe",
        "图标路径": "icons/APP302.png"
    },
    "APP303": {
        "领域": "社交沟通",
        "子功能": "互动启发",
        "应用名称": "看大戏",
        "应用路径": "flash/XC303.exe",
        "图标路径": "icons/APP303.png"
    },
    "APP304": {
        "领域": "社交沟通",
        "子功能": "互动启发",
        "应用名称": "能捕捉一切的大网",
        "应用路径": "flash/XC304.exe",
        "图标路径": "icons/APP304.png"
    },
    "APP305": {
        "领域": "社交沟通",
        "子功能": "互动启发",
        "应用名称": "颠倒歌",
        "应用路径": "flash/XC305.exe",
        "图标路径": "icons/APP305.png"
    },
    "APP306": {
        "领域": "社交沟通",
        "子功能": "互动启发",
        "应用名称": "东郭先生",
        "应用路径": "flash/XC397.exe",
        "图标路径": "icons/APP306.png"
    },
    "APP307": {
        "领域": "社交沟通",
        "子功能": "互动启发",
        "应用名称": "认识自我",
        "应用路径": "flash/XC307.exe",
        "图标路径": "icons/APP307.png"
    },
    "APP308": {
        "领域": "社交沟通",
        "子功能": "互动启发",
        "应用名称": "做衣裳",
        "应用路径": "flash/XC308.exe",
        "图标路径": "icons/APP308.png"
    },
    "APP309": {
        "领域": "社交沟通",
        "子功能": "互动启发",
        "应用名称": "卖火柴的小女孩",
        "应用路径": "flash/XC398.exe",
        "图标路径": "icons/APP309.png"
    },
    "APP310": {
        "领域": "社交沟通",
        "子功能": "互动启发",
        "应用名称": "嘟的一下看不见",
        "应用路径": "flash/XC310.exe",
        "图标路径": "icons/APP310.png"
    },
    "APP311": {
        "领域": "社交沟通",
        "子功能": "互动启发",
        "应用名称": "小火柴",
        "应用路径": "flash/XC399.exe",
        "图标路径": "icons/APP311.png"
    },
    "APP312": {
        "领域": "社交沟通",
        "子功能": "互动启发",
        "应用名称": "小脚丫，走天下",
        "应用路径": "flash/XC312.exe",
        "图标路径": "icons/APP312.png"
    },
    "APP313": {
        "领域": "社交沟通",
        "子功能": "互动启发",
        "应用名称": "早发白帝城",
        "应用路径": "flash/XC313.exe",
        "图标路径": "icons/APP313.png"
    },
    "APP314": {
        "领域": "社交沟通",
        "子功能": "互动启发",
        "应用名称": "曹冲称象",
        "应用路径": "flash/XC314.exe",
        "图标路径": "icons/APP314.png"
    },
    "APP315": {
        "领域": "社交沟通",
        "子功能": "互动启发",
        "应用名称": "渔夫和金鱼",
        "应用路径": "flash/XC315.exe",
        "图标路径": "icons/APP315.png"
    },
    "APP316": {
        "领域": "社交沟通",
        "子功能": "互动启发",
        "应用名称": "猴子抬馒头",
        "应用路径": "flash/XC316.exe",
        "图标路径": "icons/APP316.png"
    },
    "APP317": {
        "领域": "社交沟通",
        "子功能": "互动启发",
        "应用名称": "种葵花",
        "应用路径": "flash/XC317.exe",
        "图标路径": "icons/APP317.png"
    },
    "APP318": {
        "领域": "社交沟通",
        "子功能": "互动启发",
        "应用名称": "精忠报国",
        "应用路径": "flash/XC318.exe",
        "图标路径": "icons/APP318.png"
    },
    "APP319": {
        "领域": "社交沟通",
        "子功能": "互动启发",
        "应用名称": "郑和下西洋",
        "应用路径": "flash/XC319.exe",
        "图标路径": "icons/APP319.png"
    },
    "APP320": {
        "领域": "社交沟通",
        "子功能": "互动启发",
        "应用名称": "里卡多的机器人",
        "应用路径": "flash/XC320.exe",
        "图标路径": "icons/APP320.png"
    },
    "APP321": {
        "领域": "社交沟通",
        "子功能": "互动启发",
        "应用名称": "黄鼠狼拜年",
        "应用路径": "flash/XC321.exe",
        "图标路径": "icons/APP321.png"
    },
    "APP322": {
        "领域": "生活适应",
        "子功能": "安全防护",
        "应用名称": "走丢",
        "应用路径": "flash/XC322.exe",
        "图标路径": "icons/APP322.png"
    },
    "APP323": {
        "领域": "生活适应",
        "子功能": "安全防护",
        "应用名称": "危险的电",
        "应用路径": "flash/XC323.exe",
        "图标路径": "icons/APP323.png"
    },
    "APP324": {
        "领域": "生活适应",
        "子功能": "安全防护",
        "应用名称": "日常危险",
        "应用路径": "flash/XC324.exe",
        "图标路径": "icons/APP324.png"
    },
    "APP325": {
        "领域": "生活适应",
        "子功能": "安全防护",
        "应用名称": "雷电",
        "应用路径": "flash/XC325.exe",
        "图标路径": "icons/APP325.png"
    },
    "APP326": {
        "领域": "生活适应",
        "子功能": "安全防护",
        "应用名称": "暴雨",
        "应用路径": "flash/XC326.exe",
        "图标路径": "icons/APP326.png"
    },
    "APP327": {
        "领域": "生活适应",
        "子功能": "安全防护",
        "应用名称": "龙卷风",
        "应用路径": "flash/XC327.exe",
        "图标路径": "icons/APP327.png"
    },
    "APP328": {
        "领域": "生活适应",
        "子功能": "安全防护",
        "应用名称": "日月食",
        "应用路径": "flash/XC328.exe",
        "图标路径": "icons/APP328.png"
    },
    "APP329": {
        "领域": "生活适应",
        "子功能": "安全防护",
        "应用名称": "极地",
        "应用路径": "flash/XC329.exe",
        "图标路径": "icons/APP329.png"
    },
    "APP330": {
        "领域": "生活适应",
        "子功能": "安全防护",
        "应用名称": "雨水",
        "应用路径": "flash/XC330.exe",
        "图标路径": "icons/APP330.png"
    },
    "APP331": {
        "领域": "生活适应",
        "子功能": "安全防护",
        "应用名称": "智能家居",
        "应用路径": "flash/XC331.exe",
        "图标路径": "icons/APP331.png"
    },
    "APP332": {
        "领域": "生活适应",
        "子功能": "安全防护",
        "应用名称": "上学路上",
        "应用路径": "flash/XC332.exe",
        "图标路径": "icons/APP332.png"
    },
    "APP333": {
        "领域": "生活适应",
        "子功能": "安全防护",
        "应用名称": "真倒霉",
        "应用路径": "flash/XC333.exe",
        "图标路径": "icons/APP333.png"
    },
    "APP334": {
        "领域": "生活适应",
        "子功能": "安全防护",
        "应用名称": "火的诱惑",
        "应用路径": "flash/XC334.exe",
        "图标路径": "icons/APP334.png"
    },
    "APP335": {
        "领域": "生活适应",
        "子功能": "安全防护",
        "应用名称": "一个人在家时",
        "应用路径": "flash/XC335.exe",
        "图标路径": "icons/APP335.png"
    },
    "APP336": {
        "领域": "生活适应",
        "子功能": "安全防护",
        "应用名称": "电也是老虎",
        "应用路径": "flash/XC336.exe",
        "图标路径": "icons/APP336.png"
    },
    "APP337": {
        "领域": "生活适应",
        "子功能": "安全防护",
        "应用名称": "号码风波",
        "应用路径": "flash/XC337.exe",
        "图标路径": "icons/APP337.png"
    },
    "APP338": {
        "领域": "生活适应",
        "子功能": "安全防护",
        "应用名称": "寻找一双大手",
        "应用路径": "flash/XC338.exe",
        "图标路径": "icons/APP338.png"
    },
    "APP339": {
        "领域": "生活适应",
        "子功能": "安全防护",
        "应用名称": "波波的启示",
        "应用路径": "flash/XC339.exe",
        "图标路径": "icons/APP339.png"
    },
    "APP340": {
        "领域": "生活适应",
        "子功能": "生活技能",
        "应用名称": "使用家电",
        "应用路径": "flash/XC340.exe",
        "图标路径": "icons/APP340.png"
    },
    "APP341": {
        "领域": "生活适应",
        "子功能": "生活技能",
        "应用名称": "车",
        "应用路径": "flash/XC341.exe",
        "图标路径": "icons/APP341.png"
    },
    "APP342": {
        "领域": "生活适应",
        "子功能": "生活技能",
        "应用名称": "饭菜",
        "应用路径": "flash/XC342.exe",
        "图标路径": "icons/APP342.png"
    },
    "APP343": {
        "领域": "生活适应",
        "子功能": "生活技能",
        "应用名称": "鲜花",
        "应用路径": "flash/XC343.exe",
        "图标路径": "icons/APP343.png"
    },
    "APP344": {
        "领域": "生活适应",
        "子功能": "生活技能",
        "应用名称": "鱼儿",
        "应用路径": "flash/XC344.exe",
        "图标路径": "icons/APP344.png"
    },
    "APP345": {
        "领域": "生活适应",
        "子功能": "生活技能",
        "应用名称": "纸张",
        "应用路径": "flash/XC345.exe",
        "图标路径": "icons/APP345.png"
    },
    "APP346": {
        "领域": "生活适应",
        "子功能": "生活技能",
        "应用名称": "鸡蛋",
        "应用路径": "flash/XC346.exe",
        "图标路径": "icons/APP346.png"
    },
    "APP347": {
        "领域": "生活适应",
        "子功能": "生活技能",
        "应用名称": "海洋世界",
        "应用路径": "flash/XC347.exe",
        "图标路径": "icons/APP347.png"
    },
    "APP348": {
        "领域": "生活适应",
        "子功能": "生活技能",
        "应用名称": "太阳",
        "应用路径": "flash/XC348.exe",
        "图标路径": "icons/APP348.png"
    },
    "APP349": {
        "领域": "生活适应",
        "子功能": "生活技能",
        "应用名称": "寒冷地带和炎热地带",
        "应用路径": "flash/XC349.exe",
        "图标路径": "icons/APP349.png"
    },
    "APP350": {
        "领域": "生活适应",
        "子功能": "生活技能",
        "应用名称": "动物的自卫术",
        "应用路径": "flash/XC350.exe",
        "图标路径": "icons/APP350.png"
    },
    "APP351": {
        "领域": "生活适应",
        "子功能": "生活技能",
        "应用名称": "美丽的叶子",
        "应用路径": "flash/XC351.exe",
        "图标路径": "icons/APP351.png"
    },
    "APP352": {
        "领域": "生活适应",
        "子功能": "生活技能",
        "应用名称": "牙齿",
        "应用路径": "flash/XC352.exe",
        "图标路径": "icons/APP352.png"
    },
    "APP353": {
        "领域": "生活适应",
        "子功能": "生活技能",
        "应用名称": "淀粉",
        "应用路径": "flash/XC353.exe",
        "图标路径": "icons/APP353.png"
    },
    "APP354": {
        "领域": "生活适应",
        "子功能": "生活技能",
        "应用名称": "小书包",
        "应用路径": "flash/XC354.exe",
        "图标路径": "icons/APP354.png"
    },
    "APP355": {
        "领域": "生活适应",
        "子功能": "生活技能",
        "应用名称": "课间十分钟",
        "应用路径": "flash/XC355.exe",
        "图标路径": "icons/APP355.png"
    },
    "APP356": {
        "领域": "生活适应",
        "子功能": "生活技能",
        "应用名称": "离园倒计时",
        "应用路径": "flash/XC389.exe",
        "图标路径": "icons/APP356.png"
    },
    "APP357": {
        "领域": "生活适应",
        "子功能": "生活技能",
        "应用名称": "毕业典礼",
        "应用路径": "flash/XC390.exe",
        "图标路径": "icons/APP357.png"
    },
    "APP358": {
        "领域": "生活适应",
        "子功能": "生活技能",
        "应用名称": "我的书包",
        "应用路径": "flash/XC358.exe",
        "图标路径": "icons/APP358.png"
    },
    "APP359": {
        "领域": "生活适应",
        "子功能": "生活技能",
        "应用名称": "刷牙",
        "应用路径": "flash/XC359.exe",
        "图标路径": "icons/APP359.png"
    },
    "APP360": {
        "领域": "生活适应",
        "子功能": "生活技能",
        "应用名称": "放风筝",
        "应用路径": "flash/XC113.exe",
        "图标路径": "icons/APP360.png"
    },
    "APP361": {
        "领域": "生活适应",
        "子功能": "生活技能",
        "应用名称": "水资源",
        "应用路径": "flash/XC361.exe",
        "图标路径": "icons/APP361.png"
    },
    "APP362": {
        "领域": "生活适应",
        "子功能": "环境融合",
        "应用名称": "妈妈节日",
        "应用路径": "flash/XC362.exe",
        "图标路径": "icons/APP362.png"
    },
    "APP363": {
        "领域": "生活适应",
        "子功能": "环境融合",
        "应用名称": "我的节日",
        "应用路径": "flash/XC363.exe",
        "图标路径": "icons/APP363.png"
    },
    "APP364": {
        "领域": "生活适应",
        "子功能": "环境融合",
        "应用名称": "植树节",
        "应用路径": "flash/XC364.exe",
        "图标路径": "icons/APP364.png"
    },
    "APP365": {
        "领域": "生活适应",
        "子功能": "环境融合",
        "应用名称": "生肖",
        "应用路径": "flash/XC365.exe",
        "图标路径": "icons/APP365.png"
    },
    "APP366": {
        "领域": "生活适应",
        "子功能": "环境融合",
        "应用名称": "端午节",
        "应用路径": "flash/XC371.exe",
        "图标路径": "icons/APP366.png"
    },
    "APP367": {
        "领域": "生活适应",
        "子功能": "环境融合",
        "应用名称": "有趣节日",
        "应用路径": "flash/XC367.exe",
        "图标路径": "icons/APP367.png"
    },
    "APP368": {
        "领域": "生活适应",
        "子功能": "环境融合",
        "应用名称": "汉字像幅画",
        "应用路径": "flash/XC368.exe",
        "图标路径": "icons/APP368.png"
    },
    "APP369": {
        "领域": "生活适应",
        "子功能": "环境融合",
        "应用名称": "世界真精彩",
        "应用路径": "flash/XC369.exe",
        "图标路径": "icons/APP369.png"
    },
    "APP370": {
        "领域": "生活适应",
        "子功能": "环境融合",
        "应用名称": "粽意浓浓",
        "应用路径": "flash/XC370.exe",
        "图标路径": "icons/APP370.png"
    },
    "APP371": {
        "领域": "生活适应",
        "子功能": "环境融合",
        "应用名称": "佩香囊",
        "应用路径": "flash/XC372.exe",
        "图标路径": "icons/APP371.png"
    },
    "APP372": {
        "领域": "生活适应",
        "子功能": "环境融合",
        "应用名称": "在月亮上玩",
        "应用路径": "flash/XC373.exe",
        "图标路径": "icons/APP372.png"
    },
    "APP373": {
        "领域": "生活适应",
        "子功能": "环境融合",
        "应用名称": "小小发明家",
        "应用路径": "flash/XC374.exe",
        "图标路径": "icons/APP373.png"
    },
    "APP374": {
        "领域": "生活适应",
        "子功能": "环境融合",
        "应用名称": "幸福的大桌子",
        "应用路径": "flash/XC375.exe",
        "图标路径": "icons/APP374.png"
    },
    "APP375": {
        "领域": "情绪行为",
        "子功能": "自我调节",
        "应用名称": "生气",
        "应用路径": "flash/XC376.exe",
        "图标路径": "icons/APP375.png"
    },
    "APP376": {
        "领域": "情绪行为",
        "子功能": "自我调节",
        "应用名称": "快乐",
        "应用路径": "flash/XC377.exe",
        "图标路径": "icons/APP376.png"
    },
    "APP377": {
        "领域": "情绪行为",
        "子功能": "自我调节",
        "应用名称": "不怕",
        "应用路径": "flash/XC378.exe",
        "图标路径": "icons/APP377.png"
    },
    "APP378": {
        "领域": "情绪行为",
        "子功能": "自我调节",
        "应用名称": "辛苦",
        "应用路径": "flash/XC379.exe",
        "图标路径": "icons/APP378.png"
    },
    "APP379": {
        "领域": "情绪行为",
        "子功能": "自我调节",
        "应用名称": "喜欢我",
        "应用路径": "flash/XC380.exe",
        "图标路径": "icons/APP379.png"
    },
    "APP380": {
        "领域": "情绪行为",
        "子功能": "自我调节",
        "应用名称": "文明小乘客",
        "应用路径": "flash/XC411.exe",
        "图标路径": "icons/APP380.png"
    },
    "APP381": {
        "领域": "情绪行为",
        "子功能": "自我调节",
        "应用名称": "您辛苦了",
        "应用路径": "flash/XC382.exe",
        "图标路径": "icons/APP381.png"
    },
    "APP382": {
        "领域": "情绪行为",
        "子功能": "自我调节",
        "应用名称": "约定",
        "应用路径": "flash/XC383.exe",
        "图标路径": "icons/APP382.png"
    },
    "APP383": {
        "领域": "情绪行为",
        "子功能": "自我调节",
        "应用名称": "爸爸的大手",
        "应用路径": "flash/XC384.exe",
        "图标路径": "icons/APP383.png"
    },
    "APP384": {
        "领域": "情绪行为",
        "子功能": "自我调节",
        "应用名称": "我要上小学",
        "应用路径": "flash/XC385.exe",
        "图标路径": "icons/APP384.png"
    },
    "APP385": {
        "领域": "情绪行为",
        "子功能": "自我调节",
        "应用名称": "等一等哦",
        "应用路径": "flash/XC386.exe",
        "图标路径": "icons/APP385.png"
    },
    "APP386": {
        "领域": "情绪行为",
        "子功能": "自我调节",
        "应用名称": "坚持",
        "应用路径": "flash/XC387.exe",
        "图标路径": "icons/APP386.png"
    },
    "APP387": {
        "领域": "情绪行为",
        "子功能": "自我调节",
        "应用名称": "不贪心",
        "应用路径": "flash/XC388.exe",
        "图标路径": "icons/APP387.png"
    },
    "APP388": {
        "领域": "情绪行为",
        "子功能": "自我调节",
        "应用名称": "离园倒计时",
        "应用路径": "flash/XC389.exe",
        "图标路径": "icons/APP388.png"
    },
    "APP389": {
        "领域": "情绪行为",
        "子功能": "自我调节",
        "应用名称": "毕业典礼",
        "应用路径": "flash/XC390.exe",
        "图标路径": "icons/APP389.png"
    },
    "APP390": {
        "领域": "情绪行为",
        "子功能": "自我调节",
        "应用名称": "不攀比",
        "应用路径": "flash/XC391.exe",
        "图标路径": "icons/APP390.png"
    },
    "APP391": {
        "领域": "情绪行为",
        "子功能": "自我调节",
        "应用名称": "谦虚",
        "应用路径": "flash/XC392.exe",
        "图标路径": "icons/APP391.png"
    },
    "APP392": {
        "领域": "情绪行为",
        "子功能": "自我调节",
        "应用名称": "勇敢",
        "应用路径": "flash/XC393.exe",
        "图标路径": "icons/APP392.png"
    },
    "APP393": {
        "领域": "情绪行为",
        "子功能": "自我调节",
        "应用名称": "晚安！朵朵",
        "应用路径": "flash/XC394.exe",
        "图标路径": "icons/APP393.png"
    },
    "APP394": {
        "领域": "情绪行为",
        "子功能": "自我调节",
        "应用名称": "梦",
        "应用路径": "flash/XC298.exe",
        "图标路径": "icons/APP394.png"
    },
    "APP395": {
        "领域": "情绪行为",
        "子功能": "自我调节",
        "应用名称": "梦想成真之夜",
        "应用路径": "flash/XC396.exe",
        "图标路径": "icons/APP395.png"
    },
    "APP396": {
        "领域": "情绪行为",
        "子功能": "自我调节",
        "应用名称": "东郭先生",
        "应用路径": "flash/XC397.exe",
        "图标路径": "icons/APP396.png"
    },
    "APP397": {
        "领域": "情绪行为",
        "子功能": "自我调节",
        "应用名称": "卖火柴的小女孩",
        "应用路径": "flash/XC398.exe",
        "图标路径": "icons/APP397.png"
    },
    "APP398": {
        "领域": "情绪行为",
        "子功能": "自我调节",
        "应用名称": "小火柴",
        "应用路径": "flash/XC399.exe",
        "图标路径": "icons/APP398.png"
    },
    "APP399": {
        "领域": "情绪行为",
        "子功能": "情绪管理",
        "应用名称": "不乱吃东西",
        "应用路径": "flash/XC400.exe",
        "图标路径": "icons/APP399.png"
    },
    "APP400": {
        "领域": "情绪行为",
        "子功能": "情绪管理",
        "应用名称": "轻轻地，不打扰",
        "应用路径": "flash/XC401.exe",
        "图标路径": "icons/APP400.png"
    },
    "APP401": {
        "领域": "情绪行为",
        "子功能": "情绪管理",
        "应用名称": "衣服哪儿去了",
        "应用路径": "flash/XC402.exe",
        "图标路径": "icons/APP401.png"
    },
    "APP402": {
        "领域": "情绪行为",
        "子功能": "情绪管理",
        "应用名称": "小眼睛亮晶晶",
        "应用路径": "flash/XC403.exe",
        "图标路径": "icons/APP402.png"
    },
    "APP403": {
        "领域": "情绪行为",
        "子功能": "情绪管理",
        "应用名称": "玩具小鸭要回家",
        "应用路径": "flash/XC404.exe",
        "图标路径": "icons/APP403.png"
    },
    "APP404": {
        "领域": "情绪行为",
        "子功能": "情绪管理",
        "应用名称": "会说话的标识",
        "应用路径": "flash/XC405.exe",
        "图标路径": "icons/APP404.png"
    },
    "APP405": {
        "领域": "情绪行为",
        "子功能": "情绪管理",
        "应用名称": "风娃娃的心愿",
        "应用路径": "flash/XC406.exe",
        "图标路径": "icons/APP405.png"
    },
    "APP406": {
        "领域": "情绪行为",
        "子功能": "情绪管理",
        "应用名称": "我长大了",
        "应用路径": "flash/XC407.exe",
        "图标路径": "icons/APP406.png"
    },
    "APP407": {
        "领域": "情绪行为",
        "子功能": "情绪管理",
        "应用名称": "浪费不应该",
        "应用路径": "flash/XC408.exe",
        "图标路径": "icons/APP407.png"
    },
    "APP408": {
        "领域": "情绪行为",
        "子功能": "情绪管理",
        "应用名称": "有趣的筷子",
        "应用路径": "flash/XC409.exe",
        "图标路径": "icons/APP408.png"
    },
    "APP409": {
        "领域": "情绪行为",
        "子功能": "情绪管理",
        "应用名称": "我喜欢我",
        "应用路径": "flash/XC223.exe",
        "图标路径": "icons/APP409.png"
    },
    "APP410": {
        "领域": "情绪行为",
        "子功能": "情绪管理",
        "应用名称": "文明小乘客",
        "应用路径": "flash/XC411.exe",
        "图标路径": "icons/APP410.png"
    },
    "APP411": {
        "领域": "情绪行为",
        "子功能": "情绪管理",
        "应用名称": "有害的烟雾",
        "应用路径": "flash/XC412.exe",
        "图标路径": "icons/APP411.png"
    },
    "APP412": {
        "领域": "情绪行为",
        "子功能": "情绪管理",
        "应用名称": "在公共场所",
        "应用路径": "flash/XC413.exe",
        "图标路径": "icons/APP412.png"
    },
    "APP413": {
        "领域": "情绪行为",
        "子功能": "情绪管理",
        "应用名称": "我该怎么办",
        "应用路径": "flash/XC414.exe",
        "图标路径": "icons/APP413.png"
    },
    "APP414": {
        "领域": "情绪行为",
        "子功能": "情绪管理",
        "应用名称": "蚂蚁搬豆",
        "应用路径": "flash/XC415.exe",
        "图标路径": "icons/APP414.png"
    },
    "APP415": {
        "领域": "情绪行为",
        "子功能": "情绪管理",
        "应用名称": "暴雨来了",
        "应用路径": "flash/XC326.exe",
        "图标路径": "icons/APP415.png"
    },
    "APP416": {
        "领域": "情绪行为",
        "子功能": "情绪管理",
        "应用名称": "守时的孩子",
        "应用路径": "flash/XC417.exe",
        "图标路径": "icons/APP416.png"
    },
    "APP417": {
        "领域": "情绪行为",
        "子功能": "情绪管理",
        "应用名称": "光盘行动",
        "应用路径": "flash/XC418.exe",
        "图标路径": "icons/APP417.png"
    },
    "APP418": {
        "领域": "情绪行为",
        "子功能": "情绪管理",
        "应用名称": "有趣的节日",
        "应用路径": "flash/XC367.exe",
        "图标路径": "icons/APP418.png"
    }
}